lightweight_mmm/__init__.py
lightweight_mmm/conftest.py
lightweight_mmm/lightweight_mmm.py
lightweight_mmm/lightweight_mmm_test.py
lightweight_mmm/media_transforms.py
lightweight_mmm/media_transforms_test.py
lightweight_mmm/models.py
lightweight_mmm/models_test.py
lightweight_mmm/optimize_media.py
lightweight_mmm/optimize_media_test.py
lightweight_mmm/plot.py
lightweight_mmm/plot_test.py
lightweight_mmm/preprocessing.py
lightweight_mmm/preprocessing_test.py
lightweight_mmm/utils.py
lightweight_mmm/utils_test.py
lightweight_mmm/core/__init__.py
lightweight_mmm/core/core_utils.py
lightweight_mmm/core/core_utils_test.py
lightweight_mmm/core/priors.py
lightweight_mmm/core/baseline/__init__.py
lightweight_mmm/core/baseline/intercept.py
lightweight_mmm/core/baseline/intercept_test.py
lightweight_mmm/core/time/__init__.py
lightweight_mmm/core/time/seasonality.py
lightweight_mmm/core/time/seasonality_test.py
lightweight_mmm/core/time/trend.py
lightweight_mmm/core/time/trend_test.py
lightweight_mmm/core/transformations/__init__.py
lightweight_mmm/core/transformations/identity.py
lightweight_mmm/core/transformations/lagging.py
lightweight_mmm/core/transformations/lagging_test.py
lightweight_mmm/core/transformations/saturation.py
lightweight_mmm/core/transformations/saturation_test.py
lightweight_mmm-0.1.9.dist-info/LICENSE
lightweight_mmm-0.1.9.dist-info/METADATA
lightweight_mmm-0.1.9.dist-info/WHEEL
lightweight_mmm-0.1.9.dist-info/top_level.txt
lightweight_mmm-0.1.9.dist-info/RECORD
