Metadata-Version: 2.1
Name: lightweight-mmm
Version: 0.1.9
Summary: Package for Media-Mix-Modelling
Home-page: https://github.com/google/lightweight_mmm
Author: Google LLC
Author-email: no-reply@google.com
License: Apache 2.0
Classifier: Development Status :: 3 - Alpha
Classifier: Intended Audience :: Developers
Classifier: Intended Audience :: Science/Research
Classifier: License :: OSI Approved :: Apache Software License
Classifier: Topic :: Scientific/Engineering :: Mathematics
Classifier: Programming Language :: Python :: 3.8
Classifier: Programming Language :: Python :: 3.9
Classifier: Programming Language :: Python :: 3.10
License-File: LICENSE
Requires-Dist: absl-py
Requires-Dist: arviz (>=0.11.2)
Requires-Dist: immutabledict (>=2.0.0)
Requires-Dist: jax (>=0.3.18)
Requires-Dist: jaxlib (>=0.3.18)
Requires-Dist: matplotlib (==3.6.1)
Requires-Dist: numpy (>=1.23)
Requires-Dist: numpyro (>=0.9.2)
Requires-Dist: pandas (>=1.1.5)
Requires-Dist: scipy
Requires-Dist: seaborn (==0.11.1)
Requires-Dist: scikit-learn
Requires-Dist: statsmodels (>=0.13.0)
Requires-Dist: tensorflow (>=2.7.2)
